<?xml version="1.0"?>
<!DOCTYPE hibernate-mapping PUBLIC "-//Hibernate/Hibernate Mapping DTD 3.0//EN"
"http://www.hibernate.org/dtd/hibernate-mapping-3.0.dtd">
<!-- Generated Jul 9, 2015 2:35:36 PM by Hibernate Tools 4.3.1 -->
<hibernate-mapping>
    <class name="com.tmd.dao.data.VtigerModtrackerRelations" table="vtiger_modtracker_relations" catalog="vtiger" optimistic-lock="version">
        <id name="id" type="int">
            <column name="id" />
            <generator class="assigned" />
        </id>
        <property name="targetmodule" type="string">
            <column name="targetmodule" length="100" not-null="true" />
        </property>
        <property name="targetid" type="int">
            <column name="targetid" not-null="true" />
        </property>
        <property name="changedon" type="timestamp">
            <column name="changedon" length="19" />
        </property>
    </class>
</hibernate-mapping>
